vectorize_iris/__init__.py
vectorize_iris/async_client.py
vectorize_iris/client.py
vectorize_iris/exceptions.py
vectorize_iris/models.py
vectorize_iris-0.0.2.dist-info/METADATA
vectorize_iris-0.0.2.dist-info/WHEEL
vectorize_iris-0.0.2.dist-info/RECORD
